Metadata-Version: 2.1
Name: ta-core
Version: 0.1.2
Summary: Thoughtful Automation Core
Home-page: https://www.thoughtfulautomation.com/
Author: Serhii Romanets
Author-email: serhii.romanets@thoughtfulautomation.com
License: UNKNOWN
Keywords: ta_core,ta-core
Platform: UNKNOWN
Classifier: Programming Language :: Python :: 3
Classifier: License :: OSI Approved :: MIT License
Classifier: Operating System :: OS Independent
License-File: LICENSE
License-File: AUTHORS.rst
